Metadata-Version: 2.1
Name: AdaptoLogit
Version: 0.0.1
Summary: A package implementing adaptive lasso for logistic regression
Home-page: https://github.com/fernandezmaria/AdaptoLogit
Author: María Fernandez Morín; Álvaro Méndez Civieta; Rosa E. Lillo Rodriguez
Author-email: 100483781@alumnos.uc3m.es
License: GNU General Public License
Download-URL: https://github.com/fernandezmaria/AdaptoLogit/archive/0.0.1.tar.gz
Keywords: adaptive-lasso,logistic-regression,weights
Platform: UNKNOWN
Requires-Python: >=3.5
License-File: LICENSE
